aidentified_matching_api/__init__.py
aidentified_matching_api/constants.py
aidentified_matching_api/daily_files.py
aidentified_matching_api/dataset.py
aidentified_matching_api/dataset_file.py
aidentified_matching_api/get_id.py
aidentified_matching_api/token_service.py
aidentified_matching_api/validation.py
aidentified_matching_api-1.2.0.dist-info/LICENSE
aidentified_matching_api-1.2.0.dist-info/METADATA
aidentified_matching_api-1.2.0.dist-info/WHEEL
aidentified_matching_api-1.2.0.dist-info/entry_points.txt
aidentified_matching_api-1.2.0.dist-info/top_level.txt
aidentified_matching_api-1.2.0.dist-info/RECORD
