Metadata-Version: 2.1
Name: aidentified-matching-api
Version: 1.2.0
Classifier: License :: OSI Approved :: Apache Software License
Classifier: Programming Language :: Python :: 3
Requires-Python: >=3.7
License-File: LICENSE
Requires-Dist: requests (==2.*)
Requires-Dist: appdirs (==1.*)
